nostr_langchain_mcp/__init__.py
nostr_langchain_mcp/client.py
nostr_langchain_mcp/prompts.py
nostr_langchain_mcp/resources.py
nostr_langchain_mcp/tools.py
nostr_langchain_mcp-0.0.4.dist-info/licenses/LICENSE
nostr_langchain_mcp-0.0.4.dist-info/METADATA
nostr_langchain_mcp-0.0.4.dist-info/WHEEL
nostr_langchain_mcp-0.0.4.dist-info/top_level.txt
nostr_langchain_mcp-0.0.4.dist-info/RECORD
