Metadata-Version: 2.4
Name: nostr-langchain-mcp
Version: 0.0.4
Summary: Make Anthropic Model Context Protocol (MCP) tools compatible with LangChain and LangGraph agents.
Author-email: "@HallmarkBitcoin" <ehallmark1122@gmail.com>
License-Expression: MIT
Project-URL: Homepage, https://www.github.com/agentstr/nostr-langchain-mcp
Project-URL: Issues, https://www.github.com/agentstr/nostr-langchain-mcp/issues
Requires-Python: >=3.11
License-File: LICENSE
Requires-Dist: agentstr-sdk>=0.2.4
Requires-Dist: langchain-core<0.4,>=0.3.36
Requires-Dist: mcp>=1.7
Dynamic: license-file
